README.txt
ez_setup.py
setup.py
instrumentino/__init__.py
instrumentino/action.py
instrumentino/cfg.py
instrumentino/comp.py
instrumentino/executable_listctrl.py
instrumentino/log_graph.py
instrumentino/method.py
instrumentino/sequence.py
instrumentino/util.py
instrumentino.egg-info/PKG-INFO
instrumentino.egg-info/SOURCES.txt
instrumentino.egg-info/dependency_links.txt
instrumentino.egg-info/top_level.txt
instrumentino/controllers/__init__.py
instrumentino/controllers/arduino/__init__.py
instrumentino/controllers/arduino/edaq.py
instrumentino/controllers/arduino/emco.py
instrumentino/controllers/arduino/hvm.py
instrumentino/controllers/arduino/mks.py
instrumentino/controllers/arduino/parker.py
instrumentino/controllers/arduino/pewatron.py
instrumentino/controllers/arduino/pid_thermostat.py
instrumentino/controllers/arduino/pins.py
instrumentino/controllers/arduino/spellman.py
instrumentino/controllers/arduino/tecan.py
instrumentino/controllers/arduino/thermometer.py
instrumentino/controllers/labsmith_eib/__init__.py
instrumentino/controllers/labsmith_eib/labsmith_comps.py
instrumentino/resources/__init__.py
instrumentino/resources/main.xrc
instrumentino/resources/stopButton.png
instrumentino/resources/uProcessDriver.dll
instrumentino/resources/uProcessDriver_C_V1_2_1.dll