Metadata-Version: 1.1
Name: instrumentino
Version: 1.1.0
Summary: Open-source modular GUI framework for controlling Arduino based instruments
Home-page: http://www.chemie.unibas.ch/~hauser/open-source-lab/instrumentino/index.html
Author: Joel Koenka
Author-email: yoel.koenka AT gmail.com
License: GPLv3
Download-URL: https://github.com/yoelk/Instrumentino
Keywords: instrumentino arduino
Platform: UNKNOWN
Requires: wxPython
Requires: pyserial
Requires: matplotlib
Requires: numpy
